venv/__init__.py
venv/main.py
venv/webscraper.py
venv/Bot/__init__.py
venv/Bot/constants.py
venv/Bot/rune_img.py
venv/Bot/runes.py
scuttlebot-0.0.1.dist-info/METADATA
scuttlebot-0.0.1.dist-info/WHEEL
scuttlebot-0.0.1.dist-info/top_level.txt
scuttlebot-0.0.1.dist-info/RECORD
